setup.py
Liaar.egg-info/PKG-INFO
Liaar.egg-info/SOURCES.txt
Liaar.egg-info/dependency_links.txt
Liaar.egg-info/entry_points.txt
Liaar.egg-info/requires.txt
Liaar.egg-info/top_level.txt
liaar/__init__.py
liaar/liaar.py
liaar/lib/__init__.py
liaar/lib/app.py
liaar/lib/bootstrap.py
liaar/lib/exception.py
liaar/lib/logger.py
liaar/lib/parser.py
liaar/lib/path.py
liaar/lib/request_handler.py
liaar/lib/route.py
liaar/lib/setting.py
liaar/lib/twisted_handler.py
liaar/lib/url.py