Metadata-Version: 1.0
Name: Liaar
Version: 0.1.0
Summary: Create fake REST API in a minute
Home-page: https://github.com/usablica/liaar
Author: Afshin Mehrabani
Author-email: afshin.meh@gmail.com
License: LICENSE
Platform: UNKNOWN
